{
  "posts": [
    {
      "id": 1,
      "title": "json-server",
      "userId": 1
    },
    {
      "id": 2,
      "title": "json-server",
      "userId": 2
    }
  ],
  "comments": [
    {
      "id": 1,
      "body": "some comment",
      "postId": 1
    }
  ],
  "users": [
    {
      "id": 1,
      "username": "admin",
      "password": "123"
    }
  ],
  "profile": {
    "id": "1",
    "first": "jghwer12-000dhsdjahjda",
    "lastname": "2",
    "age": 465,
    "currency": "UAH",
    "country": "Poland",
    "city": "zalp",
    "username": "admin213",
    "avatar": "https://letsenhance.io/static/8f5e523ee6b2479e26ecc91b9c25261e/1015f/MainAfter.jpg"
  }
}